devs/__init__.py
devs/cli.py
devs/config.py
devs/exceptions.py
devs/core/__init__.py
devs/core/integration.py
devs/utils/__init__.py
devs_cli-1.2.1.dist-info/licenses/LICENSE
devs_cli-1.2.1.dist-info/METADATA
devs_cli-1.2.1.dist-info/WHEEL
devs_cli-1.2.1.dist-info/entry_points.txt
devs_cli-1.2.1.dist-info/top_level.txt
devs_cli-1.2.1.dist-info/RECORD
