Metadata-Version: 2.4
Name: devs-cli
Version: 1.2.1
Summary: DevContainer Management Tool - Manage multiple named devcontainers for any project
Author: Dan Lester
License-Expression: MIT
Project-URL: Homepage, https://github.com/ideonate/devs
Project-URL: Repository, https://github.com/ideonate/devs
Project-URL: Issues, https://github.com/ideonate/devs/issues
Project-URL: Documentation, https://github.com/ideonate/devs/tree/main/packages/cli
Keywords: devcontainer,docker,vscode,development
Classifier: Development Status :: 4 - Beta
Classifier: Environment :: Console
Classifier: Intended Audience :: Developers
Classifier: Operating System :: OS Independent
Classifier: Programming Language :: Python :: 3
Classifier: Programming Language :: Python :: 3.8
Classifier: Programming Language :: Python :: 3.9
Classifier: Programming Language :: Python :: 3.10
Classifier: Programming Language :: Python :: 3.11
Classifier: Programming Language :: Python :: 3.12
Classifier: Topic :: Software Development :: Libraries :: Python Modules
Classifier: Topic :: System :: Systems Administration
Requires-Python: >=3.8
License-File: LICENSE
Requires-Dist: click>=8.0.0
Requires-Dist: devs-common>=0.1.0
Requires-Dist: rich>=12.0.0
Requires-Dist: pathspec>=0.10.0
Requires-Dist: PyYAML>=6.0
Provides-Extra: dev
Requires-Dist: pytest>=6.0; extra == "dev"
Requires-Dist: pytest-cov; extra == "dev"
Requires-Dist: black; extra == "dev"
Requires-Dist: mypy; extra == "dev"
Requires-Dist: flake8; extra == "dev"
Requires-Dist: build>=0.10.0; extra == "dev"
Requires-Dist: twine>=4.0.0; extra == "dev"
Dynamic: license-file
